MANIFEST.in
README.rst
setup.py
docs/HISTORY.txt
docs/LICENSE.GPL
docs/LICENSE.txt
eea/__init__.py
eea.geotags.egg-info/PKG-INFO
eea.geotags.egg-info/SOURCES.txt
eea.geotags.egg-info/dependency_links.txt
eea.geotags.egg-info/entry_points.txt
eea.geotags.egg-info/namespace_packages.txt
eea.geotags.egg-info/not-zip-safe
eea.geotags.egg-info/requires.txt
eea.geotags.egg-info/top_level.txt
eea/geotags/README.txt
eea/geotags/__init__.py
eea/geotags/config.py
eea/geotags/configure.zcml
eea/geotags/interfaces.py
eea/geotags/overrides.zcml
eea/geotags/profiles.zcml
eea/geotags/setuphandlers.py
eea/geotags/skins.zcml
eea/geotags/version.txt
eea/geotags/behavior/__init__.py
eea/geotags/behavior/configure.zcml
eea/geotags/behavior/display.pt
eea/geotags/behavior/geotags.py
eea/geotags/behavior/input.pt
eea/geotags/behavior/widget.py
eea/geotags/browser/__init__.py
eea/geotags/browser/configure.zcml
eea/geotags/browser/app/__init__.py
eea/geotags/browser/app/basket.py
eea/geotags/browser/app/dialog.py
eea/geotags/browser/app/geojson.py
eea/geotags/browser/app/sidebar.py
eea/geotags/browser/app/suggestions.py
eea/geotags/browser/images/ajax-loader-small.gif
eea/geotags/browser/static/OpenLayers-v2.13.1.js
eea/geotags/browser/static/split.min.js
eea/geotags/browser/static/style.css
eea/geotags/browser/static/widget.js
eea/geotags/browser/static/img/blank.gif
eea/geotags/browser/static/img/close.gif
eea/geotags/browser/static/img/cloud-popup-relative.png
eea/geotags/browser/static/img/drag-rectangle-off.png
eea/geotags/browser/static/img/drag-rectangle-on.png
eea/geotags/browser/static/img/east-mini.png
eea/geotags/browser/static/img/editing_tool_bar.png
eea/geotags/browser/static/img/layer-switcher-maximize.png
eea/geotags/browser/static/img/layer-switcher-minimize.png
eea/geotags/browser/static/img/marker-blue.png
eea/geotags/browser/static/img/marker-gold.png
eea/geotags/browser/static/img/marker-green.png
eea/geotags/browser/static/img/marker.png
eea/geotags/browser/static/img/measuring-stick-off.png
eea/geotags/browser/static/img/measuring-stick-on.png
eea/geotags/browser/static/img/navigation_history.png
eea/geotags/browser/static/img/north-mini.png
eea/geotags/browser/static/img/overview_replacement.gif
eea/geotags/browser/static/img/panning-hand-off.png
